coinmarketcap_scraper_hp/__init__.py
coinmarketcap_scraper_hp/coinmarketcap.py
coinmarketcap_scraper_hp-0.0.2.dist-info/METADATA
coinmarketcap_scraper_hp-0.0.2.dist-info/WHEEL
coinmarketcap_scraper_hp-0.0.2.dist-info/top_level.txt
coinmarketcap_scraper_hp-0.0.2.dist-info/RECORD
